pyanimalconverter/__init__.py
pyanimalconverter/__main__.py
pyanimalconverter/conversation.py
pyanimalconverter/convert.py
pyanimalconverter/minmax.py
pyanimalconverter-1.13.dist-info/LICENSE
pyanimalconverter-1.13.dist-info/METADATA
pyanimalconverter-1.13.dist-info/WHEEL
pyanimalconverter-1.13.dist-info/entry_points.txt
pyanimalconverter-1.13.dist-info/top_level.txt
pyanimalconverter-1.13.dist-info/RECORD
