Metadata-Version: 2.1
Name: pyanimalconverter
Version: 1.13
Summary: A package you can use to do several kinds of unit conversions and comparison, either on their own or with the help of some animal friends.
Author-email: David Jimenez <drj8812@nyu.edu>, Sean Lee <jsl775@nyu.edu>, Madison Phung <mkp6075@nyu.edu>, Stephen Spencer-Wong <srs9979@nyu.edu>, William Xie <wx2114@nyu.edu>
License: GNU GENERAL PUBLIC LICENSE
Project-URL: Repository, https://github.com/software-students-fall2024/3-python-package-kapow
Keywords: python,package,animal,converter,units,compare
Classifier: Programming Language :: Python :: 3
Classifier: Intended Audience :: Education
Classifier: Operating System :: OS Independent
Requires-Python: >=3.11
License-File: LICENSE
Requires-Dist: pint
Provides-Extra: dev
Requires-Dist: pytest; extra == "dev"
